builder/frozen_app_icon.ico
builder/manifest.xml
builder/pyinstaller_build_macos.py
builder/pyinstaller_build_ubuntu.py
builder/pyinstaller_build_windows.py
builder/template_win_exe_version_info.txt
builder/version_info_templater.py
dist/geotribu-0.35.1.tar.gz
docs/development/contribute.md
docs/development/documentation.md
docs/development/history.md
docs/development/packaging.md
docs/development/releasing.md
docs/development/setup.md
docs/development/testing.md
docs/misc/credits.md
docs/misc/dependencies.md
docs/misc/geotribot_manifest.md
docs/misc/licenses.md
docs/static/img/geotribu_cli_logo.ico
docs/static/img/geotribu_search-image_postgis.png
docs/static/img/release_download_executable.webp
docs/usage/cli.md
docs/usage/cli_sample_rss.txt
docs/usage/cli_sample_rss_rdp.txt
docs/usage/cli_sample_search_content_advanced.txt
docs/usage/cli_sample_search_content_orfeo.txt
docs/usage/cli_sample_search_images_postgis.txt
docs/usage/cli_sample_search_images_postgis_logos_json.txt
docs/usage/configuration.md
docs/usage/examples.md
docs/usage/installation.md
geotribu-0.35.1.dist-info/licenses/LICENSE
geotribu_cli/__about__.py
geotribu_cli/__init__.py
geotribu_cli/_version.py
geotribu_cli/cli.py
geotribu_cli/cli_results_rich_formatters.py
geotribu_cli/console.py
geotribu_cli/constants.py
geotribu_cli/history.py
geotribu_cli/comments/__init__.py
geotribu_cli/comments/comments_broadcast.py
geotribu_cli/comments/comments_latest.py
geotribu_cli/comments/comments_open.py
geotribu_cli/comments/comments_toolbelt.py
geotribu_cli/comments/mdl_comment.py
geotribu_cli/content/__init__.py
geotribu_cli/content/header_check.py
geotribu_cli/content/new_article.py
geotribu_cli/content/yaml_handler.py
geotribu_cli/images/__init__.py
geotribu_cli/images/images_optimizer.py
geotribu_cli/images/optim_pillow.py
geotribu_cli/images/optim_tinify.py
geotribu_cli/json/__init__.py
geotribu_cli/json/json_client.py
geotribu_cli/rss/__init__.py
geotribu_cli/rss/mdl_rss.py
geotribu_cli/rss/rss_reader.py
geotribu_cli/search/__init__.py
geotribu-0.35.1.dist-info/METADATA
geotribu-0.35.1.dist-info/WHEEL
geotribu-0.35.1.dist-info/entry_points.txt
geotribu-0.35.1.dist-info/top_level.txt
geotribu-0.35.1.dist-info/RECORD
