Metadata-Version: 2.4
Name: geotribu
Version: 0.35.1
Summary: Une ligne de commande pour Geotribu qui offre des outils pour rechercher et consulter les contenus et images, et faciliter les tâches récurrentes des contributeur/ices.
Author-email: "Julien Moura (Geotribu)" <geotribu@gmail.com>
License-Expression: MIT
Project-URL: Homepage, https://cli.geotribu.fr/
Project-URL: Documentation, https://cli.geotribu.fr/
Project-URL: Repository, https://github.com/geotribu/cli/
Project-URL: Bug Reports, https://github.com/geotribu/cli/issues/
Keywords: cli,Geotribu,GIS,images,lunr,Mastodon,markdown,Pillow,search,tinify
Classifier: Development Status :: 4 - Beta
Classifier: Environment :: Console
Classifier: Intended Audience :: Information Technology
Classifier: Operating System :: OS Independent
Classifier: Programming Language :: Python :: 3
Classifier: Programming Language :: Python :: 3.10
Classifier: Programming Language :: Python :: 3.11
Classifier: Programming Language :: Python :: 3.12
Classifier: Programming Language :: Python :: 3.13
Classifier: Topic :: Scientific/Engineering :: GIS
Requires-Python: >=3.10
License-File: LICENSE
Requires-Dist: argcomplete<4,>=3.6.3
Requires-Dist: imagesize<1.5,>=1.4.1
Requires-Dist: lunr[languages]<0.9,>=0.8.0
Requires-Dist: markdownify<1.3,>=1.2.2
Requires-Dist: Mastodon.py<2.2,>=2.1.4
Requires-Dist: orjson<3.12,>=3.11.4
Requires-Dist: packaging<26,>=25
Requires-Dist: rich_argparse<1.8,>=1.7.2
Requires-Dist: python-frontmatter<2,>=1.1.0
Requires-Dist: requests<3,>=2.32.5
Requires-Dist: typing-extensions<5,>=4.15; python_version < "3.11"
Provides-Extra: dev
Requires-Dist: black; extra == "dev"
Requires-Dist: flake8>=7.1.0; extra == "dev"
Requires-Dist: flake8-bugbear<26,>=23; extra == "dev"
Requires-Dist: flake8-builtins>=2; extra == "dev"
Requires-Dist: flake8-docstrings>=1.6; extra == "dev"
Requires-Dist: flake8-eradicate>=1; extra == "dev"
Requires-Dist: flake8-isort>=5; extra == "dev"
Requires-Dist: Flake8-pyproject>=1.2.3; extra == "dev"
Requires-Dist: pre-commit>=4; extra == "dev"
Provides-Extra: doc
Requires-Dist: furo==2025.*; extra == "doc"
Requires-Dist: matplotlib<4,>=3.8.2; extra == "doc"
Requires-Dist: myst-parser[linkify]>=2; extra == "doc"
Requires-Dist: sphinx-argparse-cli>=1; extra == "doc"
Requires-Dist: sphinx-autobuild>=2024; extra == "doc"
Requires-Dist: sphinx-autodoc-typehints<4; extra == "doc"
Requires-Dist: sphinx-copybutton>=0.5.2; extra == "doc"
Requires-Dist: sphinxcontrib-mermaid>=1.0.0; extra == "doc"
Requires-Dist: sphinxext-opengraph>=0.13.0; extra == "doc"
Requires-Dist: sphinx-sitemap>=2.4.0; extra == "doc"
Provides-Extra: test
Requires-Dist: Pillow<13,>=10.2; extra == "test"
Requires-Dist: pytest-cov>=4; extra == "test"
Requires-Dist: pytest-retry>=1.6; extra == "test"
Requires-Dist: validators<0.36,>=0.20; extra == "test"
Provides-Extra: packaging
Requires-Dist: build<2,>=1.2.2; extra == "packaging"
Requires-Dist: distro==1.9.*; sys_platform == "linux" and extra == "packaging"
Requires-Dist: pyinstaller<6.18,>=6.14.2; extra == "packaging"
Requires-Dist: pyinstaller-hooks-contrib==2025.*; extra == "packaging"
Requires-Dist: pypiwin32==223; sys_platform == "win32" and extra == "packaging"
Provides-Extra: all
Requires-Dist: tinify<2,>=1.6; extra == "all"
Requires-Dist: Pillow<13,>=10.0.1; extra == "all"
Provides-Extra: img-local
Requires-Dist: Pillow<13,>=10.0.1; extra == "img-local"
Provides-Extra: img-remote
Requires-Dist: tinify<2,>=1.6; extra == "img-remote"
Dynamic: license-file
